[
  {
    "id": 1,
    "title": "Greek Salad",
    "image": "https://images.pexels.com/photos/1213710/pexels-photo-1213710.jpeg?auto=compress&cs=tinysrgb&w=1600",
    "price": 12.99,
    "description": "The famous greek salad of crispy lettuce, peppers, olives and our Chicago style feta cheese, garnished with crunchy garlic and rosemary croutons."
  },
  {
    "id": 2,
    "title": "Bruschetta",
    "image": "https://images.pexels.com/photos/3535373/pexels-photo-3535373.jpeg?auto=compress&cs=tinysrgb&w=1600",
    "price": 5.99,
    "description": "Our Bruschetta is made from grilled bread that has been smeared with garlic and seasoned with salt and olive oil."
  },
  {
    "id": 3,
    "title": "Energy Bowl",
    "image": "https://images.pexels.com/photos/1099680/pexels-photo-1099680.jpeg?auto=compress&cs=tinysrgb&w=1600",
    "price": 14.99,
    "description": "This comes straight from grandma’s recipe book, every last ingredient has been sourced and is as authentic as can be imagined."
  }
]
